{"type":"Topology","arcs":[[[580,641],[-10,-120],[0,-153],[114,1],[0,-113],[26,-61],[-15,-48],[25,-68],[-27,-28],[-18,29],[-85,-22],[-92,-58],[-28,35],[-53,-21],[-20,65],[-53,59],[25,57],[-52,12],[26,71],[-131,2],[-32,25],[-77,10],[-2,40],[-101,334],[102,4],[-4,20],[88,-2],[49,17],[30,-26],[7,-58],[103,-5],[56,20],[149,-18]]],"transform":{"scale":[0.00015090416666665933,0.0001392857142857215],"translate":[113.785289,35.223271]},"objects":{"json":{"type":"GeometryCollection","geometries":[{"arcs":[[0]],"type":"Polygon","properties":{"adcode":410703,"level":"district","name":"卫滨区","pinyin":"weibinqu","parent":{"adcode":410700},"childrenNum":0,"center":[113.865666,35.301796],"centroid":[113.865666,35.301796]}}]}}}