{"type":"Topology","arcs":[[[237,352],[-57,57],[-2,89],[-86,25],[-83,83],[11,36],[-20,26],[17,26],[136,15],[116,-1],[77,20],[67,70],[28,4],[80,-73],[61,-22],[12,-78],[-3,-81],[25,-49],[72,-55],[80,-12],[26,-71],[-9,-36],[-93,21],[5,-60],[28,-27],[10,-183],[-41,-76],[-24,14],[-60,126],[-33,25],[-59,15],[-62,53],[-64,-27],[-64,81],[-91,65]]],"transform":{"scale":[0.0007228173803526378,0.0006414476309226907],"translate":[105.24858500000002,25.563285000000004]},"objects":{"json":{"type":"GeometryCollection","geometries":[{"arcs":[[0]],"type":"Polygon","properties":{"adcode":520424,"level":"district","name":"关岭布依族苗族自治县","pinyin":"guanlingbuyizumiaozuzizhixian","parent":{"adcode":520400},"childrenNum":0,"center":[105.538335,25.953518],"centroid":[105.538335,25.953518]}}]}}}